mootdx/__init__.py
mootdx/__main__.py
mootdx/affair.py
mootdx/cache/__init__.py
mootdx/cache/compat.py
mootdx/cache/file.py
mootdx/cache/timed.py
mootdx/cache/timer.py
mootdx/config.py
mootdx/consts.py
mootdx/contrib/__init__.py
mootdx/contrib/adjust.py
mootdx/contrib/compat.py
mootdx/exceptions.py
mootdx/financial/__init__.py
mootdx/financial/base.py
mootdx/financial/columns.py
mootdx/financial/financial.py
mootdx/logger.py
mootdx/parse.py
mootdx/quotes.py
mootdx/reader.py
mootdx/server.py
mootdx/tools/DownloadTDXCaiWu.py
mootdx/tools/__init__.py
mootdx/tools/customize.py
mootdx/tools/reversion.py
mootdx/tools/tdx2csv.py
mootdx/utils/__init__.py
mootdx/utils/adjust.py
mootdx/utils/factor.py
mootdx/utils/holiday.js
mootdx/utils/holiday.py
mootdx/version.py
mootdx-0.11.4.dist-info/AUTHORS.rst
mootdx-0.11.4.dist-info/LICENSE
mootdx-0.11.4.dist-info/METADATA
mootdx-0.11.4.dist-info/WHEEL
mootdx-0.11.4.dist-info/entry_points.txt
mootdx-0.11.4.dist-info/RECORD
