Metadata-Version: 2.1
Name: mootdx
Version: 0.11.4
Summary: 通达信数据读取接口.
Home-page: https://www.mootdx.com
License: MIT
Author: bopo
Author-email: ibopo@126.com
Requires-Python: >=3.8,<4.0
Classifier: Development Status :: 2 - Pre-Alpha
Classifier: Intended Audience :: Developers
Classifier: License :: OSI Approved :: MIT License
Classifier: Natural Language :: English
Classifier: Programming Language :: Python :: 3
Classifier: Programming Language :: Python :: 3.8
Classifier: Programming Language :: Python :: 3.9
Classifier: Programming Language :: Python :: 3.10
Classifier: Programming Language :: Python :: 3.11
Classifier: Programming Language :: Python :: 3.12
Classifier: Programming Language :: Python :: 3.6
Classifier: Programming Language :: Python :: 3.7
Provides-Extra: all
Provides-Extra: cli
Provides-Extra: fetch
Requires-Dist: click (>=8.1.3,<9.0.0) ; extra == "cli" or extra == "all"
Requires-Dist: httpx[socks] (>=0.25.0,<0.26.0)
Requires-Dist: prettytable (>=3.5.0,<4.0.0) ; extra == "cli" or extra == "all"
Requires-Dist: py-mini-racer (>=0.6.0,<0.7.0) ; extra == "fetch" or extra == "all"
Requires-Dist: tdxpy (>=0.2.5,<0.3.0)
Requires-Dist: tenacity (>=8.1.0,<9.0.0)
Requires-Dist: tqdm
Requires-Dist: typing-extensions (>=4.5.0,<5.0.0)
Project-URL: Repository, https://github.com/mootdx/mootdx
